README.md
setup.py
SICA/__init__.py
SICA/sica.py
SICA/ssica.py
SICAtest02.egg-info/PKG-INFO
SICAtest02.egg-info/SOURCES.txt
SICAtest02.egg-info/dependency_links.txt
SICAtest02.egg-info/requires.txt
SICAtest02.egg-info/top_level.txt