Metadata-Version: 1.0
Name: SICAtest02
Version: 0.0.2
Summary: An feature extraction algorithm,   local repo testing
Home-page: https://github.com/yifanff/sica_test_0513
Author: Yifan
Author-email: yifanff@126.com
License: MIT Licence test
Keywords: pip_test,SICA_test,featureextraction_test,test!!
Platform: any
